.bumpversion.cfg
.virtualenv.dev-requirements.txt
.virtualenv.requirements.txt
LICENSE
MANIFEST.in
Makefile
README.rst
setup.cfg
setup.py
tox.ini
doc/build/man/kiwi::system::stackbuild.8
doc/build/man/kiwi::system::stash.8
kiwi_stackbuild_plugin/__init__.py
kiwi_stackbuild_plugin/defaults.py
kiwi_stackbuild_plugin/exceptions.py
kiwi_stackbuild_plugin/version.py
kiwi_stackbuild_plugin.egg-info/PKG-INFO
kiwi_stackbuild_plugin.egg-info/SOURCES.txt
kiwi_stackbuild_plugin.egg-info/dependency_links.txt
kiwi_stackbuild_plugin.egg-info/entry_points.txt
kiwi_stackbuild_plugin.egg-info/not-zip-safe
kiwi_stackbuild_plugin.egg-info/requires.txt
kiwi_stackbuild_plugin.egg-info/top_level.txt
kiwi_stackbuild_plugin/tasks/__init__.py
kiwi_stackbuild_plugin/tasks/system_stackbuild.py
kiwi_stackbuild_plugin/tasks/system_stash.py
package/python-kiwi_stackbuild_plugin-rpmlintrc
package/python-kiwi_stackbuild_plugin-spec-template
package/python-kiwi_stackbuild_plugin.changes