Metadata-Version: 2.1
Name: kiwi_stackbuild_plugin
Version: 1.0.10
Summary: KIWI - Stack Build Plugin
Home-page: https://github.com/OSInside/kiwi-stackbuild-plugin
Download-URL: https://download.opensuse.org/repositories/Virtualization:/Appliances:/Builder
Author: Marcus Schaefer
Author-email: ms@suse.com
License: GPLv3+
Classifier: Development Status :: 5 - Production/Stable
Classifier: Intended Audience :: Developers
Classifier: License :: OSI Approved :: GNU General Public License v3 or later (GPLv3+)
Classifier: Operating System :: POSIX :: Linux
Classifier: Programming Language :: Python :: 3.6
Classifier: Programming Language :: Python :: 3.8
Classifier: Topic :: System :: Operating System
License-File: LICENSE
Requires-Dist: docopt
Requires-Dist: mock
Requires-Dist: kiwi>=9.23.0
